alteredai/AlteredAiDataLoader.py
alteredai/AlteredAiPytorch.py
alteredai/AlteredAiTensorflow.py
alteredai/DataTransformations.py
alteredai/__init__.py
alteredai/utilities.py
alteredai-0.0.5.dist-info/LICENSE.txt
alteredai-0.0.5.dist-info/METADATA
alteredai-0.0.5.dist-info/WHEEL
alteredai-0.0.5.dist-info/top_level.txt
alteredai-0.0.5.dist-info/RECORD
