Metadata-Version: 2.1
Name: alteredai
Version: 0.0.5
Summary: basic package
Home-page: UNKNOWN
Author: Mayank Sharma
Author-email: mmayank.sharma18@gmail.com
License: UNKNOWN
Platform: UNKNOWN
Classifier: Programming Language :: Python :: 3
Classifier: License :: OSI Approved :: MIT License
Classifier: Operating System :: OS Independent
